email_free_fast_email/__init__.py
email_free_fast_email-1.1.0.dist-info/METADATA
email_free_fast_email-1.1.0.dist-info/WHEEL
email_free_fast_email-1.1.0.dist-info/top_level.txt
email_free_fast_email-1.1.0.dist-info/RECORD
