Metadata-Version: 2.1
Name: email_free_fast_email
Version: 1.1.0
Home-page: https://github.com/alikushbaev/send_email_free/blob/main/README.md
Author: alikushbaev
Author-email: alikushbaev3@gmail.com
Classifier: Programming Language :: Python :: 3
Classifier: License :: OSI Approved :: MIT License
Classifier: Operating System :: OS Independent
Requires-Python: >=3.11
